CricCatapult/Cricsheet.py
CricCatapult/Location.py
CricCatapult/Player.py
CricCatapult/Records.py
CricCatapult/Scoreboard.py
CricCatapult/Series.py
CricCatapult/__init__.py
criccatapult-0.0.8.dist-info/METADATA
criccatapult-0.0.8.dist-info/WHEEL
criccatapult-0.0.8.dist-info/top_level.txt
criccatapult-0.0.8.dist-info/RECORD
