Metadata-Version: 2.1
Name: criccatapult
Version: 0.0.8
Summary: Package for cricket analytics
Author: Aadrij Upadya, Pradyum Chitlu
Author-email: <adrij2005@gmail.com>
Keywords: python,cricket,sports analytics,data analytics,visualiation,geospatial data,GIS
Classifier: Development Status :: 3 - Alpha
Classifier: Intended Audience :: Science/Research
Classifier: Programming Language :: Python :: 3
Classifier: Operating System :: Unix
Classifier: Operating System :: MacOS :: MacOS X
Classifier: Operating System :: Microsoft :: Windows
Requires-Dist: pandas
Requires-Dist: numpy
Requires-Dist: matplotlib
Requires-Dist: requests
Requires-Dist: bs4
Requires-Dist: folium
Requires-Dist: seaborn
Requires-Dist: pygame
Requires-Dist: shapely
